{
  "_class": "shapePath",
  "booleanOperation": -1,
  "clippingMaskMode": 0,
  "do_objectID": "A75ED9D9-F659-4848-82DF-6675A8BBFBD4",
  "edited": true,
  "exportOptions": {
    "_class": "exportOptions",
    "do_objectID": "A61111C4-33D4-4EC2-9349-BD82AE9AA070",
    "exportFormats": [
    ],
    "includedLayerIds": [
    ],
    "layerOptions": 0,
    "shouldTrim": false
  },
  "frame": {
    "_class": "rect",
    "constrainProportions": false,
    "do_objectID": "E19531BE-0BF2-456C-9481-9470DB867366",
    "height": 1.162393162393158,
    "width": 74.53815261044183,
    "x": 69.87951807228917,
    "y": 61.02564102564099
  },
  "hasClippingMask": false,
  "isClosed": false,
  "isFixedToViewport": false,
  "isFlippedHorizontal": false,
  "isFlippedVertical": false,
  "isLocked": false,
  "isVisible": true,
  "layerListExpandedType": 0,
  "name": "Line",
  "nameIsFixed": false,
  "pointRadiusBehaviour": 1,
  "points": [
    {
      "_class": "curvePoint",
      "cornerRadius": 0,
      "curveFrom": "{-1.1123914289701275e-16, 0.5}",
      "curveMode": 1,
      "curveTo": "{-1.1123914289701275e-16, 0.5}",
      "hasCurveFrom": false,
      "hasCurveTo": false,
      "point": "{-1.1123914289701275e-16, 0.5}"
    },
    {
      "_class": "curvePoint",
      "cornerRadius": 0,
      "curveFrom": "{-1.1123914289701275e-16, 0.5}",
      "curveMode": 1,
      "curveTo": "{-1.1123914289701275e-16, 0.5}",
      "hasCurveFrom": false,
      "hasCurveTo": false,
      "point": "{1, 0.5}"
    }
  ],
  "resizingConstraint": 63,
  "resizingType": 0,
  "rotation": 0,
  "shouldBreakMaskChain": false,
  "style": {
    "_class": "style",
    "borderOptions": {
      "_class": "borderOptions",
      "dashPattern": [
      ],
      "do_objectID": "2AC947E8-F028-4E65-BEDF-589DDB1110CD",
      "isEnabled": false,
      "lineCapStyle": 2,
      "lineJoinStyle": 0
    },
    "borders": [
      {
        "_class": "border",
        "color": {
          "_class": "color",
          "alpha": 1,
          "blue": 0.3058823529411765,
          "green": 0.2196078431372548,
          "red": 0.1098039215686274
        },
        "fillType": 0,
        "isEnabled": true,
        "position": 0,
        "thickness": 2
      }
    ],
    "do_objectID": "A87A3083-4145-4070-83DB-4C8EAE6A870B",
    "endDecorationType": 2,
    "endMarkerType": 2,
    "fills": [
      {
        "_class": "fill",
        "color": {
          "_class": "color",
          "alpha": 1,
          "blue": 0.847,
          "green": 0.847,
          "red": 0.847
        },
        "fillType": 0,
        "isEnabled": false,
        "noiseIndex": 0,
        "noiseIntensity": 0,
        "patternFillType": 1,
        "patternTileScale": 1
      }
    ],
    "miterLimit": 10,
    "startDecorationType": 0,
    "startMarkerType": 0,
    "windingRule": 1
  }
}